json2latex/__init__.py
json2latex/escape.py
json2latex/python2latex.py
json2latex-0.0.3.data/scripts/json2latex
json2latex-0.0.3.dist-info/licenses/LICENSE
json2latex-0.0.3.dist-info/METADATA
json2latex-0.0.3.dist-info/WHEEL
json2latex-0.0.3.dist-info/top_level.txt
json2latex-0.0.3.dist-info/RECORD
