Metadata-Version: 2.4
Name: json2latex
Version: 0.0.3
Summary: A package for converting JSON and other similar structures to a format accessible using LaTeX.
Home-page: https://github.com/CameronDevine/json2latex
Author: Cameron Devine
Author-email: camerondtrain@gmail.com
Classifier: License :: OSI Approved :: BSD License
Classifier: Operating System :: OS Independent
Classifier: Topic :: Text Processing :: Markup :: LaTeX
License-File: LICENSE
Requires-Dist: roman
Dynamic: author
Dynamic: author-email
Dynamic: classifier
Dynamic: description
Dynamic: description-content-type
Dynamic: home-page
Dynamic: license-file
Dynamic: requires-dist
Dynamic: summary
